{
  "main": {
    "id": "b208ffbe60835d4f",
    "type": "split",
    "children": [
      {
        "id": "553ff509beff5da6",
        "type": "tabs",
        "children": [
          {
            "id": "38df220ec2d41f53",
            "type": "leaf",
            "state": {
              "type": "graph",
              "state": {},
              "icon": "lucide-git-fork",
              "title": "Visualização em gráfico"
            }
          }
        ]
      }
    ],
    "direction": "vertical"
  },
  "left": {
    "id": "15ba34008f2b2007",
    "type": "split",
    "children": [
      {
        "id": "6c84abe3e940e128",
        "type": "tabs",
        "children": [
          {
            "id": "da6701288be2bada",
            "type": "leaf",
            "state": {
              "type": "file-explorer",
              "state": {
                "sortOrder": "alphabetical",
                "autoReveal": false
              },
              "icon": "lucide-folder-closed",
              "title": "Explorador de arquivos"
            }
          },
          {
            "id": "9b9f1061599d8d4f",
            "type": "leaf",
            "state": {
              "type": "search",
              "state": {
                "query": "",
                "matchingCase": false,
                "explainSearch": false,
                "collapseAll": false,
                "extraContext": false,
                "sortOrder": "alphabetical"
              },
              "icon": "lucide-search",
              "title": "Search"
            }
          },
          {
            "id": "8181e462f6b9d829",
            "type": "leaf",
            "state": {
              "type": "bookmarks",
              "state": {},
              "icon": "lucide-bookmark",
              "title": "Marcadores"
            }
          }
        ]
      }
    ],
    "direction": "horizontal",
    "width": 338.5
  },
  "right": {
    "id": "6993a9c1dbf7838b",
    "type": "split",
    "children": [
      {
        "id": "5c7ec8bc4ef9609a",
        "type": "tabs",
        "children": [
          {
            "id": "00d8a685a3fe1772",
            "type": "leaf",
            "state": {
              "type": "backlink",
              "state": {
                "file": "Unicap/Unicap.md",
                "collapseAll": false,
                "extraContext": false,
                "sortOrder": "alphabetical",
                "showSearch": false,
                "searchQuery": "",
                "backlinkCollapsed": false,
                "unlinkedCollapsed": true
              },
              "icon": "links-coming-in",
              "title": "Links inversos para Unicap"
            }
          },
          {
            "id": "11f6a6a2433ac6b0",
            "type": "leaf",
            "state": {
              "type": "outgoing-link",
              "state": {
                "file": "Unicap/Unicap.md",
                "linksCollapsed": false,
                "unlinkedCollapsed": true
              },
              "icon": "links-going-out",
              "title": "Links de saída para Unicap"
            }
          },
          {
            "id": "60231deedce5276f",
            "type": "leaf",
            "state": {
              "type": "tag",
              "state": {
                "sortOrder": "frequency",
                "useHierarchy": true,
                "showSearch": false,
                "searchQuery": ""
              },
              "icon": "lucide-tags",
              "title": "Tags"
            }
          },
          {
            "id": "8c310b27a51ff673",
            "type": "leaf",
            "state": {
              "type": "outline",
              "state": {
                "file": "Unicap/Unicap.md",
                "followCursor": false,
                "showSearch": false,
                "searchQuery": ""
              },
              "icon": "lucide-list",
              "title": "Sumário de Unicap"
            }
          }
        ],
        "currentTab": 3
      }
    ],
    "direction": "horizontal",
    "width": 300,
    "collapsed": true
  },
  "left-ribbon": {
    "hiddenItems": {
      "bases:Criar nova base": false,
      "switcher:Abrir a troca rápida": false,
      "graph:Abrir visualização em gráfico": false,
      "canvas:Criar novo canvas": false,
      "daily-notes:Abrir a nota de hoje": false,
      "templates:Inserir modelo": false,
      "command-palette:Abrir paleta de comandos": false
    }
  },
  "active": "38df220ec2d41f53",
  "lastOpenFiles": [
    "Unicap/Graduação/6º Período/Ciência dos Dados.md",
    "Eduardo/Contas.md",
    "Eduardo/Untitled.md",
    "Eduardo/Sem título.base",
    "Eduardo/Senhas.base",
    "Eduardo/Sem título.md",
    "Unicap/PIBIC/PIBIC.md",
    "Unicap/Graduação/Graduação.md",
    "Unicap/PIBIC/Isolation Forest/Isolation Forest.md",
    "Unicap/PIBIC/Learning From Data/Learning From Data.md",
    "To Do.md",
    "Unicap/Graduação/5º Período/Projeto Integrador/Lounge do Açaí.md",
    "Unicap/Graduação/5º Período/Projeto Integrador/Projeto Integrador.md",
    "Unicap/Graduação/5º Período/5º Período.md",
    "Unicap/Graduação/6º Período/PDAE/Projeto de Desenvolvimento Ágil e Eficaz.md",
    "Cursos/React Testing Library and Jest.md",
    "Cursos/Cursos.md",
    "Unicap/Maratona/Texto de encerramento.md",
    "Unicap/Maratona/Maratona.md",
    "Unicap/Graduação/6º Período/Arquitetura de Sistemas/Arquitetura de Sistemas.md",
    "Unicap/Maratona/Bits.md",
    "Unicap/Graduação/6º Período/PDAE/Lojinha IA.md",
    "Unicap/Graduação/6º Período/PDAE/Modelo de Criacao - Base de Cálculo.png",
    "Unicap/Graduação/6º Período/PDAE/Modelo de Criacao - Business Case.pdf",
    "Unicap/Graduação/6º Período/PDAE/Modelo de Criacao - Blueprint.pdf",
    "Unicap/Graduação/6º Período/PDAE/Images/Modelo de Curva de ROI - Business Case.jpg",
    "Unicap/Graduação/6º Período/PDAE/Images/Lojinha IA - Business Case.jpg",
    "Unicap/Graduação/6º Período/PDAE/Modelo de Ficha - Business Case 1.pptx",
    "Unicap/Graduação/6º Período/PDAE/Modelo de Ficha - Business Case.pptx",
    "Unicap/Graduação/6º Período/Arquitetura de Sistemas/Data Streaming - Roteiro Apresentação.md",
    "Unicap/Graduação/6º Período/Arquitetura de Sistemas/Data Streaming em Tempo Real com Apache Kafka.pdf",
    "Unicap/Graduação/6º Período/Arquitetura de Sistemas",
    "Unicap/Maratona/Sem título.base",
    "Unicap/Maratona/Sem título 1.base",
    "README.md",
    "Unicap/PIBIC/Isolation Forest/Isolation Forest - Apresentação.md",
    "Queen/Testes QP.md",
    "Unicap/Unicap.md",
    "Pasted image 20250901202837.png",
    "Unicap/Graduação/6º Período/Images/Modelo de Ficha - Business Case.jpg",
    "Pasted image 20250901202258.png",
    "Pasted image 20250812013214.png",
    "Pasted image 20250530000837.png",
    "Untitled.canvas"
  ]
}